ddm/__init__.py
ddm/accumulator.py
ddm/amp.py
ddm/api.py
ddm/dataset.py
ddm/ema.py
ddm/layers.py
ddm/modules.py
ddm/ops.py
ddm/trainer.py
ddm/utils.py
ddm/models/__init__.py
ddm/models/gussion_diffusion.py
ddm/models/unet.py
tests/__init__.py
tests/test_ddpm.py
tests/test_trainer.py
denoising_diffusion_mindspore-0.0.1a0.dist-info/LICENSE
denoising_diffusion_mindspore-0.0.1a0.dist-info/METADATA
denoising_diffusion_mindspore-0.0.1a0.dist-info/WHEEL
denoising_diffusion_mindspore-0.0.1a0.dist-info/top_level.txt
denoising_diffusion_mindspore-0.0.1a0.dist-info/RECORD
